{
  "target": {
    "key": "ogn:ogn-165-298:cemetery-attendant",
    "name": "Cemetery Attendant",
    "setId": "OGN",
    "setSlug": "Origins",
    "setLabel": "Origins",
    "publicCode": "ogn-165-298",
    "riftboundId": "ogn-165-298",
    "cardSlug": "Cemetery-Attendant",
    "url": "https://www.cardmarket.com/es/Riftbound/Products/Singles/Origins/Cemetery-Attendant"
  },
  "url": "https://www.cardmarket.com/es/Riftbound/Products/Singles/Origins/Cemetery-Attendant?sellerCountry=10&language=1&minCondition=2&isFoil=Y",
  "parsed": {
    "status": 403,
    "ok": false,
    "headers": {
      "cache-control": "private, max-age=0, no-store, no-cache, must-revalidate, post-check=0, pre-check=0",
      "cf-ray": "a18674beacfb77fd-IAD",
      "connection": "keep-alive",
      "content-encoding": "br",
      "content-type": "text/html; charset=UTF-8",
      "date": "Thu, 09 Jul 2026 09:55:57 GMT",
      "expires": "Thu, 01 Jan 1970 00:00:01 GMT",
      "referrer-policy": "same-origin",
      "server": "cloudflare",
      "server-timing": "cfEdge;dur=1,cfOrigin;dur=0",
      "set-cookie": "__cf_bm=5CRxG3lCVSF6VnJNwP5rhKf0VXH7Ci0sTV4Hn72Q9EA-1783590957.8677769-1.0.1.1-O9Sv7eCfi51ekynWcNZciXFa3X_eJBGA1Q4tk.7BAUl6ot5LmxXas4emoFN3m2l.c9nkrbkwD08A7dsQJR6.iW.r83IOfcWGmkLGCrYmFGStGH4sx8.HEq2DMz0aPDGa; HttpOnly; SameSite=None; Secure; Path=/; Domain=cardmarket.com; Expires=Thu, 09 Jul 2026 10:25:57 GMT",
      "transfer-encoding": "chunked",
      "vary": "accept-encoding",
      "x-frame-options": "SAMEORIGIN"
    }
  }
}