{
  "target": {
    "key": "ogn:ogn-103-298:ravenbloom-student",
    "name": "Ravenbloom Student",
    "setId": "OGN",
    "setSlug": "Origins",
    "setLabel": "Origins",
    "publicCode": "ogn-103-298",
    "riftboundId": "ogn-103-298",
    "cardSlug": "Ravenbloom-Student",
    "url": "https://www.cardmarket.com/es/Riftbound/Products/Singles/Origins/Ravenbloom-Student"
  },
  "url": "https://www.cardmarket.com/es/Riftbound/Products/Singles/Origins/Ravenbloom-Student?sellerCountry=10&language=1&minCondition=2&isFoil=Y",
  "parsed": {
    "status": 403,
    "ok": false,
    "headers": {
      "cache-control": "private, max-age=0, no-store, no-cache, must-revalidate, post-check=0, pre-check=0",
      "cf-ray": "a17600f8bc9657f4-IAD",
      "connection": "keep-alive",
      "content-encoding": "br",
      "content-type": "text/html; charset=UTF-8",
      "date": "Tue, 07 Jul 2026 10:00:43 GMT",
      "expires": "Thu, 01 Jan 1970 00:00:01 GMT",
      "referrer-policy": "same-origin",
      "server": "cloudflare",
      "server-timing": "cfEdge;dur=4,cfOrigin;dur=0",
      "set-cookie": "__cf_bm=pe1cJroBfhpib0ViwedFonEHAAQ8LuEeXPNy_P.dK0c-1783418443.6417565-1.0.1.1-LC83iym5X8eE.wkayVUW3qlGt52eWMXWOFyM1HhjB2Qc12JTl9gAq3Mzu4Q9XdqLL613W9OcQo8wpynMO3SwYP_o9Xr57tZcxeSAFpFDI8Ty.cxg9o4J6hvcfPG2eMSq; HttpOnly; SameSite=None; Secure; Path=/; Domain=cardmarket.com; Expires=Tue, 07 Jul 2026 10:30:43 GMT",
      "transfer-encoding": "chunked",
      "vary": "accept-encoding",
      "x-frame-options": "SAMEORIGIN"
    }
  }
}