{
  "target": {
    "key": "ogn:ogn-048-298:meditation",
    "name": "Meditation",
    "setId": "OGN",
    "setSlug": "Origins",
    "setLabel": "Origins",
    "publicCode": "ogn-048-298",
    "riftboundId": "ogn-048-298",
    "cardSlug": "Meditation",
    "url": "https://www.cardmarket.com/es/Riftbound/Products/Singles/Origins/Meditation"
  },
  "url": "https://www.cardmarket.com/es/Riftbound/Products/Singles/Origins/Meditation?sellerCountry=10&language=1&minCondition=2&isFoil=Y",
  "parsed": {
    "status": 403,
    "ok": false,
    "headers": {
      "cache-control": "private, max-age=0, no-store, no-cache, must-revalidate, post-check=0, pre-check=0",
      "cf-ray": "a16e1be4cc4ddadb-ORD",
      "connection": "keep-alive",
      "content-encoding": "br",
      "content-type": "text/html; charset=UTF-8",
      "date": "Mon, 06 Jul 2026 11:01:00 GMT",
      "expires": "Thu, 01 Jan 1970 00:00:01 GMT",
      "referrer-policy": "same-origin",
      "server": "cloudflare",
      "server-timing": "cfEdge;dur=1,cfOrigin;dur=0",
      "set-cookie": "__cf_bm=m5ZTJ6bECxH3gYBn_QdLBOtlnBeTflH0kbd6QcknRH8-1783335660.28422-1.0.1.1-SNd0_9Fj..lXroJlkMdS.QLC6VmUv.6f42D4v9NrSfLMW3AmdT_a.pnUyGgJO0rFP1cPAYDmEOW2czYOjgeT7qiqHVl1lkcnx8QRTitYaaNSOp.AMjsMH9RIX0DmN4HK; HttpOnly; SameSite=None; Secure; Path=/; Domain=cardmarket.com; Expires=Mon, 06 Jul 2026 11:31:00 GMT",
      "transfer-encoding": "chunked",
      "vary": "accept-encoding",
      "x-frame-options": "SAMEORIGIN"
    }
  }
}