{
  "target": {
    "key": "ogn:ogn-096-298:watchful-sentry",
    "name": "Watchful Sentry",
    "setId": "OGN",
    "setSlug": "Origins",
    "setLabel": "Origins",
    "publicCode": "ogn-096-298",
    "riftboundId": "ogn-096-298",
    "cardSlug": "Watchful-Sentry",
    "url": "https://www.cardmarket.com/es/Riftbound/Products/Singles/Origins/Watchful-Sentry"
  },
  "url": "https://www.cardmarket.com/es/Riftbound/Products/Singles/Origins/Watchful-Sentry?sellerCountry=10&language=1&minCondition=2&isFoil=Y",
  "parsed": {
    "status": 403,
    "ok": false,
    "headers": {
      "cache-control": "private, max-age=0, no-store, no-cache, must-revalidate, post-check=0, pre-check=0",
      "cf-ray": "a1760046baab2fdf-IAD",
      "connection": "keep-alive",
      "content-encoding": "br",
      "content-type": "text/html; charset=UTF-8",
      "date": "Tue, 07 Jul 2026 10:00:15 GMT",
      "expires": "Thu, 01 Jan 1970 00:00:01 GMT",
      "referrer-policy": "same-origin",
      "server": "cloudflare",
      "server-timing": "cfEdge;dur=1,cfOrigin;dur=0",
      "set-cookie": "__cf_bm=xgo4nSSOdjb1G.mnbJZ66IhfzmR1be0oILnt6GkKqSg-1783418415.1595721-1.0.1.1-BBE..5wa9Cngp7fLDgBCm2PRunMfP.3EF4XQy_avN2JknBWjznq7rB7LaGsMG3WUza5e8cGmviR_kYlxlkAFimhkdczOd3yrbt.zgx.XMyyBHhjNGb3OG9zMNs5U7Ug6; HttpOnly; SameSite=None; Secure; Path=/; Domain=cardmarket.com; Expires=Tue, 07 Jul 2026 10:30:15 GMT",
      "transfer-encoding": "chunked",
      "vary": "accept-encoding",
      "x-frame-options": "SAMEORIGIN"
    }
  }
}