{
  "target": {
    "key": "ogn:ogn-074-298:taric-protector",
    "name": "Taric - Protector",
    "setId": "OGN",
    "setSlug": "Origins",
    "setLabel": "Origins",
    "publicCode": "ogn-074-298",
    "riftboundId": "ogn-074-298",
    "cardSlug": "Taric-Protector",
    "url": "https://www.cardmarket.com/es/Riftbound/Products/Singles/Origins/Taric-Protector"
  },
  "url": "https://www.cardmarket.com/es/Riftbound/Products/Singles/Origins/Taric-Protector?sellerCountry=10&language=1&minCondition=2&isFoil=Y",
  "parsed": {
    "status": 403,
    "ok": false,
    "headers": {
      "cache-control": "private, max-age=0, no-store, no-cache, must-revalidate, post-check=0, pre-check=0",
      "cf-ray": "a16e1e7b0f80da7a-ORD",
      "connection": "keep-alive",
      "content-encoding": "br",
      "content-type": "text/html; charset=UTF-8",
      "date": "Mon, 06 Jul 2026 11:02:46 GMT",
      "expires": "Thu, 01 Jan 1970 00:00:01 GMT",
      "referrer-policy": "same-origin",
      "server": "cloudflare",
      "server-timing": "cfEdge;dur=1,cfOrigin;dur=0",
      "set-cookie": "__cf_bm=dqoqbUfBgdqyOZerrR3jO_Tam9H58yJ5NLwDrXixgDM-1783335766.2415807-1.0.1.1-i3YayL_NEoEbgZ.cFWUWFaOL7EUi54BNog_UkDPVIt84qO7UwRFAR1_b_iEKiOx8g6QmNW37zMa0RdDsF8uCI2.43xPeLOLRbHLqpbk.d.mpTlyIXvAIKdzNUjSFd5Xj; HttpOnly; SameSite=None; Secure; Path=/; Domain=cardmarket.com; Expires=Mon, 06 Jul 2026 11:32:46 GMT",
      "transfer-encoding": "chunked",
      "vary": "accept-encoding",
      "x-frame-options": "SAMEORIGIN"
    }
  }
}