{
  "target": {
    "key": "ogn:ogn-006-298:flame-chompers",
    "name": "Flame Chompers",
    "setId": "OGN",
    "setSlug": "Origins",
    "setLabel": "Origins",
    "publicCode": "ogn-006-298",
    "riftboundId": "ogn-006-298",
    "cardSlug": "Flame-Chompers",
    "url": "https://www.cardmarket.com/es/Riftbound/Products/Singles/Origins/Flame-Chompers"
  },
  "url": "https://www.cardmarket.com/es/Riftbound/Products/Singles/Origins/Flame-Chompers?sellerCountry=10&language=1&minCondition=2&isFoil=Y",
  "parsed": {
    "status": 403,
    "ok": false,
    "headers": {
      "cache-control": "private, max-age=0, no-store, no-cache, must-revalidate, post-check=0, pre-check=0",
      "cf-ray": "a1654cafec46826e-IAD",
      "connection": "keep-alive",
      "content-encoding": "br",
      "content-type": "text/html; charset=UTF-8",
      "date": "Sun, 05 Jul 2026 09:21:27 GMT",
      "expires": "Thu, 01 Jan 1970 00:00:01 GMT",
      "referrer-policy": "same-origin",
      "server": "cloudflare",
      "server-timing": "cfEdge;dur=2,cfOrigin;dur=0",
      "set-cookie": "__cf_bm=Gf_hok0d7dLYzDL8OLCzEnPNzjAla1TboE.bzkt9omk-1783243287.0280387-1.0.1.1-1lgR4WKSO72D2XTm59N6ALEKO9LK3Y0UrzWBEQvyoNCrSym04fFQhRyaP1rQrbJpOJWz9hpDytiZXApMK6ncx0sAr4zJBcd7PLFTqwhwMZ7pggF9BUFzJw3uPvEVJd4j; HttpOnly; SameSite=None; Secure; Path=/; Domain=cardmarket.com; Expires=Sun, 05 Jul 2026 09:51:27 GMT",
      "transfer-encoding": "chunked",
      "vary": "accept-encoding",
      "x-frame-options": "SAMEORIGIN"
    }
  }
}