{
  "target": {
    "key": "ogn:ogn-094-298:sprite-call",
    "name": "Sprite Call",
    "setId": "OGN",
    "setSlug": "Origins",
    "setLabel": "Origins",
    "publicCode": "ogn-094-298",
    "riftboundId": "ogn-094-298",
    "cardSlug": "Sprite-Call",
    "url": "https://www.cardmarket.com/es/Riftbound/Products/Singles/Origins/Sprite-Call"
  },
  "url": "https://www.cardmarket.com/es/Riftbound/Products/Singles/Origins/Sprite-Call?sellerCountry=10&language=1&minCondition=2&isFoil=Y",
  "parsed": {
    "status": 403,
    "ok": false,
    "headers": {
      "cache-control": "private, max-age=0, no-store, no-cache, must-revalidate, post-check=0, pre-check=0",
      "cf-ray": "a1760013fd5eb114-IAD",
      "connection": "keep-alive",
      "content-encoding": "br",
      "content-type": "text/html; charset=UTF-8",
      "date": "Tue, 07 Jul 2026 10:00:07 GMT",
      "expires": "Thu, 01 Jan 1970 00:00:01 GMT",
      "referrer-policy": "same-origin",
      "server": "cloudflare",
      "server-timing": "cfEdge;dur=1,cfOrigin;dur=0",
      "set-cookie": "__cf_bm=xEX3BoziAhBb2NPkS4sVTAybatR4IAfNXz01qA8iZSI-1783418407.0392637-1.0.1.1-TzboQ1GUzZP3lpy7Q.KDqZcyZbRX_i3TFrWDXG3BLHzQEIM4JjdN0TNb3dVVcL5pizXeiTrKXhlgQ8wNNG4wVd5DS7k_.tuzvux5mY.QLJ4dnRMe0F9lArGbljhhOg4t; HttpOnly; SameSite=None; Secure; Path=/; Domain=cardmarket.com; Expires=Tue, 07 Jul 2026 10:30:07 GMT",
      "transfer-encoding": "chunked",
      "vary": "accept-encoding",
      "x-frame-options": "SAMEORIGIN"
    }
  }
}