{
  "target": {
    "key": "ogn:ogn-026-298:brynhir-thundersong",
    "name": "Brynhir Thundersong",
    "setId": "OGN",
    "setSlug": "Origins",
    "setLabel": "Origins",
    "publicCode": "ogn-026-298",
    "riftboundId": "ogn-026-298",
    "cardSlug": "Brynhir-Thundersong",
    "url": "https://www.cardmarket.com/es/Riftbound/Products/Singles/Origins/Brynhir-Thundersong"
  },
  "url": "https://www.cardmarket.com/es/Riftbound/Products/Singles/Origins/Brynhir-Thundersong?sellerCountry=10&language=1&minCondition=2&isFoil=Y",
  "parsed": {
    "status": 403,
    "ok": false,
    "headers": {
      "cache-control": "private, max-age=0, no-store, no-cache, must-revalidate, post-check=0, pre-check=0",
      "cf-ray": "a1654eae6f1da9d6-IAD",
      "connection": "keep-alive",
      "content-encoding": "br",
      "content-type": "text/html; charset=UTF-8",
      "date": "Sun, 05 Jul 2026 09:22:48 GMT",
      "expires": "Thu, 01 Jan 1970 00:00:01 GMT",
      "referrer-policy": "same-origin",
      "server": "cloudflare",
      "server-timing": "cfEdge;dur=1,cfOrigin;dur=0",
      "set-cookie": "__cf_bm=dW62SAq0NbwajjPsbCoDFLD3VtdXD6LADlL27W6OJj4-1783243368.70861-1.0.1.1-P0dFdRl9xyGEEQQBryxblW6uKbd_dV1C6RhjKBUHlBL4d05aMB5X37_PrlNs.awBe5CIygC_CpxM1DVz.9LUqx8g6Hkx1AjYrRraDFCTVc3ZohI_QREfaoqxFe1wMM6t; HttpOnly; SameSite=None; Secure; Path=/; Domain=cardmarket.com; Expires=Sun, 05 Jul 2026 09:52:48 GMT",
      "transfer-encoding": "chunked",
      "vary": "accept-encoding",
      "x-frame-options": "SAMEORIGIN"
    }
  }
}