{
  "target": {
    "key": "ogs:ogs-014-024:lux-crownguard",
    "name": "Lux - Crownguard",
    "setId": "OGS",
    "setSlug": "Proving-Grounds",
    "setLabel": "Proving Grounds",
    "publicCode": "ogs-014-024",
    "riftboundId": "ogs-014-024",
    "cardSlug": "Lux-Crownguard",
    "url": "https://www.cardmarket.com/es/Riftbound/Products/Singles/Proving-Grounds/Lux-Crownguard"
  },
  "url": "https://www.cardmarket.com/es/Riftbound/Products/Singles/Proving-Grounds/Lux-Crownguard?sellerCountry=10&language=1&minCondition=2&isFoil=Y",
  "parsed": {
    "status": 403,
    "ok": false,
    "headers": {
      "cache-control": "private, max-age=0, no-store, no-cache, must-revalidate, post-check=0, pre-check=0",
      "cf-ray": "a19eb0efb8dd889a-LAX",
      "connection": "keep-alive",
      "content-encoding": "br",
      "content-type": "text/html; charset=UTF-8",
      "date": "Sun, 12 Jul 2026 08:31:21 GMT",
      "expires": "Thu, 01 Jan 1970 00:00:01 GMT",
      "referrer-policy": "same-origin",
      "server": "cloudflare",
      "server-timing": "cfEdge;dur=2,cfOrigin;dur=0",
      "set-cookie": "__cf_bm=N1_33wJOLRiF3uqhPwip4zKF0K7uoJIhAxVxJa7PXxY-1783845081.5592842-1.0.1.1-bFBteyeJl7dFZh9kGz2U3Yd9h3VY9fdlEjV9CJsTDCqOPsGSe86sBzrhB512ELH_W4n9ZCcM.Z8rU8BK8qlPaGEF4L2tEh7WJRpRlNzwAi1mogCTA6fL7iKPX1Jomg8f; HttpOnly; SameSite=None; Secure; Path=/; Domain=cardmarket.com; Expires=Sun, 12 Jul 2026 09:01:21 GMT",
      "transfer-encoding": "chunked",
      "vary": "accept-encoding",
      "x-frame-options": "SAMEORIGIN"
    }
  }
}