{
  "target": {
    "key": "sfd:sfd-133-221:boots-of-swiftness",
    "name": "Boots of Swiftness",
    "setId": "SFD",
    "setSlug": "Spiritforged",
    "setLabel": "Spiritforged",
    "publicCode": "sfd-133-221",
    "riftboundId": "sfd-133-221",
    "cardSlug": "Boots-of-Swiftness",
    "url": "https://www.cardmarket.com/es/Riftbound/Products/Singles/Spiritforged/Boots-of-Swiftness"
  },
  "url": "https://www.cardmarket.com/es/Riftbound/Products/Singles/Spiritforged/Boots-of-Swiftness?sellerCountry=10&language=1&minCondition=2&isFoil=Y",
  "parsed": {
    "status": 403,
    "ok": false,
    "headers": {
      "cache-control": "private, max-age=0, no-store, no-cache, must-revalidate, post-check=0, pre-check=0",
      "cf-ray": "a1b770f7b9648c9d-IAD",
      "connection": "keep-alive",
      "content-encoding": "br",
      "content-type": "text/html; charset=UTF-8",
      "date": "Wed, 15 Jul 2026 08:36:45 GMT",
      "expires": "Thu, 01 Jan 1970 00:00:01 GMT",
      "referrer-policy": "same-origin",
      "server": "cloudflare",
      "server-timing": "cfEdge;dur=1,cfOrigin;dur=0",
      "set-cookie": "__cf_bm=2gqdyfFDG79cn3P66CrK182_RVdV4fuYnJBX4vf9RrA-1784104605.3983812-1.0.1.1-DC9xiTnhrhZr8LLyGAgjNTfrRr9ZED1p4fxInfL25u3ooUOVCLKkw0Ai0yn.x8JOM_hP9fwMK9VvH6ONTA1wtEPvvQloCPWjvwxielLBwAcRVQYttCuUT6RIw9WcWe5.; HttpOnly; SameSite=None; Secure; Path=/; Domain=cardmarket.com; Expires=Wed, 15 Jul 2026 09:06:45 GMT",
      "transfer-encoding": "chunked",
      "vary": "accept-encoding",
      "x-frame-options": "SAMEORIGIN"
    }
  }
}