{
  "target": {
    "key": "sfd:sfd-195-221:irelia-blade-dancer",
    "name": "Irelia - Blade Dancer",
    "setId": "SFD",
    "setSlug": "Spiritforged",
    "setLabel": "Spiritforged",
    "publicCode": "sfd-195-221",
    "riftboundId": "sfd-195-221",
    "cardSlug": "Irelia-Blade-Dancer",
    "url": "https://www.cardmarket.com/es/Riftbound/Products/Singles/Spiritforged/Irelia-Blade-Dancer"
  },
  "url": "https://www.cardmarket.com/es/Riftbound/Products/Singles/Spiritforged/Irelia-Blade-Dancer?sellerCountry=10&language=1&minCondition=2&isFoil=Y",
  "parsed": {
    "status": 403,
    "ok": false,
    "headers": {
      "cache-control": "private, max-age=0, no-store, no-cache, must-revalidate, post-check=0, pre-check=0",
      "cf-ray": "a1348eea5dc60cda-ORD",
      "connection": "keep-alive",
      "content-encoding": "br",
      "content-type": "text/html; charset=UTF-8",
      "date": "Mon, 29 Jun 2026 11:23:17 GMT",
      "expires": "Thu, 01 Jan 1970 00:00:01 GMT",
      "referrer-policy": "same-origin",
      "server": "cloudflare",
      "server-timing": "cfEdge;dur=2,cfOrigin;dur=0",
      "set-cookie": "__cf_bm=nbk6xSa8IOlWOLjLxAeNGDXk4ySnBowqsfevT24ieoU-1782732197.4980316-1.0.1.1-IZgoc3RBXohDRcWXVTQlP3V2j58Ha7u2RZ2r8js1GaSfcFvvmxM_iETZnB5RUNhQn83VEioDITJqI83W_lIP5yGUTskkCXtVLJvZG60ZSdaQd6a9mJ9zfLi61qGck7.7; HttpOnly; SameSite=None; Secure; Path=/; Domain=cardmarket.com; Expires=Mon, 29 Jun 2026 11:53:17 GMT",
      "transfer-encoding": "chunked",
      "vary": "accept-encoding",
      "x-frame-options": "SAMEORIGIN"
    }
  }
}