{
  "target": {
    "key": "sfd:sfd-134-221:cull",
    "name": "Cull",
    "setId": "SFD",
    "setSlug": "Spiritforged",
    "setLabel": "Spiritforged",
    "publicCode": "sfd-134-221",
    "riftboundId": "sfd-134-221",
    "cardSlug": "Cull",
    "url": "https://www.cardmarket.com/es/Riftbound/Products/Singles/Spiritforged/Cull"
  },
  "url": "https://www.cardmarket.com/es/Riftbound/Products/Singles/Spiritforged/Cull?sellerCountry=10&language=1&minCondition=2&isFoil=Y",
  "parsed": {
    "status": 403,
    "ok": false,
    "headers": {
      "cache-control": "private, max-age=0, no-store, no-cache, must-revalidate, post-check=0, pre-check=0",
      "cf-ray": "a1b771128a2ac987-IAD",
      "connection": "keep-alive",
      "content-encoding": "br",
      "content-type": "text/html; charset=UTF-8",
      "date": "Wed, 15 Jul 2026 08:36:49 GMT",
      "expires": "Thu, 01 Jan 1970 00:00:01 GMT",
      "referrer-policy": "same-origin",
      "server": "cloudflare",
      "server-timing": "cfEdge;dur=3,cfOrigin;dur=0",
      "set-cookie": "__cf_bm=wIqz3FTgHf3QPPwOdpIDVuUKTtpIiCOtO0AZMDB1bPg-1784104609.6873686-1.0.1.1-QOVWc9xcXH.zOMK9CaJnos1oOPfEKktXfOCL4GeLz6NOUCbet338ac_Ei8DfYUHV4jjutozFbhZtLSV1DT6kWhzjWuedV1YOhd6TpUIkKjvNmk0StPIAqLAfoRbiudHp; HttpOnly; SameSite=None; Secure; Path=/; Domain=cardmarket.com; Expires=Wed, 15 Jul 2026 09:06:49 GMT",
      "transfer-encoding": "chunked",
      "vary": "accept-encoding",
      "x-frame-options": "SAMEORIGIN"
    }
  }
}