{
  "target": {
    "key": "unl:unl-014-219:monster-harpoon",
    "name": "Monster Harpoon",
    "setId": "UNL",
    "setSlug": "Unleashed",
    "setLabel": "Unleashed",
    "publicCode": "unl-014-219",
    "riftboundId": "unl-014-219",
    "cardSlug": "Monster-Harpoon",
    "url": "https://www.cardmarket.com/es/Riftbound/Products/Singles/Unleashed/Monster-Harpoon"
  },
  "url": "https://www.cardmarket.com/es/Riftbound/Products/Singles/Unleashed/Monster-Harpoon?sellerCountry=10&language=1&minCondition=2&isFoil=Y",
  "parsed": {
    "status": 403,
    "ok": false,
    "headers": {
      "cache-control": "private, max-age=0, no-store, no-cache, must-revalidate, post-check=0, pre-check=0",
      "cf-ray": "a1cffcf75ebe9db4-IAD",
      "connection": "keep-alive",
      "content-encoding": "br",
      "content-type": "text/html; charset=UTF-8",
      "date": "Sat, 18 Jul 2026 08:06:37 GMT",
      "expires": "Thu, 01 Jan 1970 00:00:01 GMT",
      "referrer-policy": "same-origin",
      "server": "cloudflare",
      "server-timing": "cfEdge;dur=1,cfOrigin;dur=0",
      "set-cookie": "__cf_bm=c35__2pnZoI749cA6ggbuG52X_wD_lNFVd.MQiD9Ofs-1784361997.9772468-1.0.1.1-4FYObm0H3M3FME9UPu7zFt8an_xYnc6ooYSRAbfDjNNAZrftsPYa5V_G0iH8Lwm4U5XHVwwfJNwyCEdttuNlPKBH40Ceo5ICcC90v4y9aYJLV7z8hh7r0wyvVpjq6fxl; HttpOnly; SameSite=None; Secure; Path=/; Domain=cardmarket.com; Expires=Sat, 18 Jul 2026 08:36:37 GMT",
      "transfer-encoding": "chunked",
      "vary": "accept-encoding",
      "x-frame-options": "SAMEORIGIN"
    }
  }
}