{
  "target": {
    "key": "unl:unl-113-219:master-yi-tempered",
    "name": "Master Yi - Tempered",
    "setId": "UNL",
    "setSlug": "Unleashed",
    "setLabel": "Unleashed",
    "publicCode": "unl-113-219",
    "riftboundId": "unl-113-219",
    "cardSlug": "Master-Yi-Tempered",
    "url": "https://www.cardmarket.com/es/Riftbound/Products/Singles/Unleashed/Master-Yi-Tempered"
  },
  "url": "https://www.cardmarket.com/es/Riftbound/Products/Singles/Unleashed/Master-Yi-Tempered?sellerCountry=10&language=1&minCondition=2&isFoil=Y",
  "parsed": {
    "status": 403,
    "ok": false,
    "headers": {
      "cache-control": "private, max-age=0, no-store, no-cache, must-revalidate, post-check=0, pre-check=0",
      "cf-ray": "a14ca3bc4c6d2419-IAD",
      "connection": "keep-alive",
      "content-encoding": "br",
      "content-type": "text/html; charset=UTF-8",
      "date": "Thu, 02 Jul 2026 09:31:48 GMT",
      "expires": "Thu, 01 Jan 1970 00:00:01 GMT",
      "referrer-policy": "same-origin",
      "server": "cloudflare",
      "server-timing": "cfEdge;dur=2,cfOrigin;dur=0",
      "set-cookie": "__cf_bm=dCcmN052iXHFXVkWMFP5Hr3DbniH7BI5FhlS5sG9Ig8-1782984708.5280287-1.0.1.1-r021qdBk2eXCqt2P4Ok7e9LJrnLthTSxgsxIB3O09clMtBjGWraDucrsRV8jXvst1zSJWGnRxLX2mSY55oiBKR1lxPnQ8XHZdm_hi0KvIEyYmmPhd8Yh74MSt4TInFzh; HttpOnly; SameSite=None; Secure; Path=/; Domain=cardmarket.com; Expires=Thu, 02 Jul 2026 10:01:48 GMT",
      "transfer-encoding": "chunked",
      "vary": "accept-encoding",
      "x-frame-options": "SAMEORIGIN"
    }
  }
}