{
  "target": {
    "key": "unl:unl-217-219:trapping-grounds",
    "name": "Trapping Grounds",
    "setId": "UNL",
    "setSlug": "Unleashed",
    "setLabel": "Unleashed",
    "publicCode": "unl-217-219",
    "riftboundId": "unl-217-219",
    "cardSlug": "Trapping-Grounds",
    "url": "https://www.cardmarket.com/es/Riftbound/Products/Singles/Unleashed/Trapping-Grounds"
  },
  "url": "https://www.cardmarket.com/es/Riftbound/Products/Singles/Unleashed/Trapping-Grounds?sellerCountry=10&language=1&minCondition=2&isFoil=Y",
  "parsed": {
    "status": 403,
    "ok": false,
    "headers": {
      "cache-control": "private, max-age=0, no-store, no-cache, must-revalidate, post-check=0, pre-check=0",
      "cf-ray": "a1f12aac0dec0d9d-IAD",
      "connection": "keep-alive",
      "content-encoding": "br",
      "content-type": "text/html; charset=UTF-8",
      "date": "Wed, 22 Jul 2026 08:45:00 GMT",
      "expires": "Thu, 01 Jan 1970 00:00:01 GMT",
      "referrer-policy": "same-origin",
      "server": "cloudflare",
      "server-timing": "cfEdge;dur=1,cfOrigin;dur=0",
      "set-cookie": "__cf_bm=EPhpFZLgldW0JCr6U.KTiQ7x9XsN.PqteX9Mb8UWTfw-1784709900.163594-1.0.1.1-yO81x.TYJQLvHnDcFJRyv_tVbGgbvbudxVYlGTo2xmlCbycK1_tsreAfAb5_IawRZ3WUDtFGio_QJgiaQp_0rihijIR87u40.F2POH1V1rMgiL_xU2WIx0sPmMqvT7Vu; HttpOnly; SameSite=None; Secure; Path=/; Domain=cardmarket.com; Expires=Wed, 22 Jul 2026 09:15:00 GMT",
      "transfer-encoding": "chunked",
      "vary": "accept-encoding",
      "x-frame-options": "SAMEORIGIN"
    }
  }
}