{
  "target": {
    "key": "unl:unl-094-219:gemhand-hunter",
    "name": "Gemhand Hunter",
    "setId": "UNL",
    "setSlug": "Unleashed",
    "setLabel": "Unleashed",
    "publicCode": "unl-094-219",
    "riftboundId": "unl-094-219",
    "cardSlug": "Gemhand-Hunter",
    "url": "https://www.cardmarket.com/es/Riftbound/Products/Singles/Unleashed/Gemhand-Hunter"
  },
  "url": "https://www.cardmarket.com/es/Riftbound/Products/Singles/Unleashed/Gemhand-Hunter?sellerCountry=10&language=1&minCondition=2&isFoil=Y",
  "parsed": {
    "status": 403,
    "ok": false,
    "headers": {
      "cache-control": "private, max-age=0, no-store, no-cache, must-revalidate, post-check=0, pre-check=0",
      "cf-ray": "a14ca1e4dd65a0e7-IAD",
      "connection": "keep-alive",
      "content-encoding": "br",
      "content-type": "text/html; charset=UTF-8",
      "date": "Thu, 02 Jul 2026 09:30:33 GMT",
      "expires": "Thu, 01 Jan 1970 00:00:01 GMT",
      "referrer-policy": "same-origin",
      "server": "cloudflare",
      "server-timing": "cfEdge;dur=1,cfOrigin;dur=0",
      "set-cookie": "__cf_bm=NhjkqkXYGzll7CIYLj5xuPudAYj4XhYZUyacwdOTP4M-1782984633.0969021-1.0.1.1-jQC7Mb1aKpxUAaG1XF9ei_VXriac3GaDIvsKE9zNadtnF3y1emf5EHQC2hZrRAwtY_umCjt.gKsvZbMLwgfY__bDQbCsmn_T8PdKDo8w7ojP1qJNUd4jAXxIAqo8Topc; HttpOnly; SameSite=None; Secure; Path=/; Domain=cardmarket.com; Expires=Thu, 02 Jul 2026 10:00:33 GMT",
      "transfer-encoding": "chunked",
      "vary": "accept-encoding",
      "x-frame-options": "SAMEORIGIN"
    }
  }
}