{
  "target": {
    "key": "unl:unl-044-219:flurry-of-feathers",
    "name": "Flurry of Feathers",
    "setId": "UNL",
    "setSlug": "Unleashed",
    "setLabel": "Unleashed",
    "publicCode": "unl-044-219",
    "riftboundId": "unl-044-219",
    "cardSlug": "Flurry-of-Feathers",
    "url": "https://www.cardmarket.com/es/Riftbound/Products/Singles/Unleashed/Flurry-of-Feathers"
  },
  "url": "https://www.cardmarket.com/es/Riftbound/Products/Singles/Unleashed/Flurry-of-Feathers?sellerCountry=10&language=1&minCondition=2&isFoil=Y",
  "parsed": {
    "status": 403,
    "ok": false,
    "headers": {
      "cache-control": "private, max-age=0, no-store, no-cache, must-revalidate, post-check=0, pre-check=0",
      "cf-ray": "a13c54932b795d13-IAD",
      "connection": "keep-alive",
      "content-encoding": "br",
      "content-type": "text/html; charset=UTF-8",
      "date": "Tue, 30 Jun 2026 10:01:33 GMT",
      "expires": "Thu, 01 Jan 1970 00:00:01 GMT",
      "referrer-policy": "same-origin",
      "server": "cloudflare",
      "server-timing": "cfEdge;dur=2,cfOrigin;dur=0",
      "set-cookie": "__cf_bm=_qaiCO9I1.yj_LB.31OSlsZ2sRB6n9qtHmDxPDo9lzk-1782813693.949392-1.0.1.1-j0Ps78kfZKRAuCFzOsybiIEsyFujlVl9fpP7p21rxWbJUbI21Jhy4KesgrLbiJ9YCGFPNM0TJKMUfSm3T70M0UfyfLmId4hExs.oDR8fqyJ98nG8K5L56IoZWbFCwl08; HttpOnly; SameSite=None; Secure; Path=/; Domain=cardmarket.com; Expires=Tue, 30 Jun 2026 10:31:33 GMT",
      "transfer-encoding": "chunked",
      "vary": "accept-encoding",
      "x-frame-options": "SAMEORIGIN"
    }
  }
}